SwarmPlus/__init__.py
SwarmPlus/agent.py
SwarmPlus/demo.py
SwarmPlus/helper.py
SwarmPlus/memory.py
SwarmPlus/models.py
SwarmPlus/vectorestores.py
SwarmPlus/tools/AgenticTools.py
SwarmPlus/tools/CodeInterpreter.py
SwarmPlus/tools/FileOperationsTool.py
SwarmPlus/tools/PythonTool.py
SwarmPlus/tools/TerminalTool.py
SwarmPlus/tools/__init__.py
SwarmPlus/utils/__init__.py
SwarmPlus/utils/response_model.py
Swarm_Plus-0.1.0.dist-info/LICENSE.txt
Swarm_Plus-0.1.0.dist-info/METADATA
Swarm_Plus-0.1.0.dist-info/WHEEL
Swarm_Plus-0.1.0.dist-info/top_level.txt
Swarm_Plus-0.1.0.dist-info/RECORD
