Metadata-Version: 2.1
Name: Swarm-Plus
Version: 0.1.0
Summary: Swarm-Plus is a Python framework developed by Vishnu Durairaj. for developing AI agents equipped with specialized roles and tools to handle complex user requests efficiently.
Author: Vishnu.D
Author-email: 
License: MIT
Keywords: pip install Swarm-Plus,pip install Swarm Plus,Swarm-Plus,AI Agent Framework Swarm-Plus,Multi Agent Framework
Classifier: Development Status :: 3 - Alpha
Classifier: Intended Audience :: Developers
Classifier: Topic :: Software Development :: Build Tools
Classifier: License :: OSI Approved :: MIT License
Classifier: Programming Language :: Python :: 3.12
License-File: LICENSE.txt
Requires-Dist: openai==1.40.1
Requires-Dist: anthropic==0.34.1
Requires-Dist: pandas==2.2.2
Requires-Dist: pydantic==2.8.2
Requires-Dist: pybase64==1.4.0
Requires-Dist: requests==2.32.3
Requires-Dist: tiktoken==0.7.0
Requires-Dist: chainlit==1.3.1
Requires-Dist: websocket-client==1.8.0
Requires-Dist: lxml==5.3.0
Requires-Dist: notebook==7.2.1
Requires-Dist: groq==0.11.0
Requires-Dist: httpx==0.27.2
Requires-Dist: chromadb==0.5.11
Requires-Dist: sentence-transformers==3.1.1
Requires-Dist: marshmallow==3.23.1
